customate/__init__.py
customate/error.py
customate/api_resources/__init__.py
customate/api_resources/api_requester.py
customate/api_resources/mixins.py
customate/api_resources/abstract/__init__.py
customate/api_resources/abstract/domain.py
customate/rest/__init__.py
customate/rest/business/__init__.py
customate/rest/currency_exchange/__init__.py
customate/rest/direct_debit_funding_source/__init__.py
customate/rest/direct_debit_to_wallet_payment/__init__.py
customate/rest/direct_debit_to_wallet_schedule/__init__.py
customate/rest/funding_source/__init__.py
customate/rest/non_processing_date/__init__.py
customate/rest/open_banking_mandate/__init__.py
customate/rest/open_banking_mandate_provider/__init__.py
customate/rest/open_banking_provider/__init__.py
customate/rest/open_banking_to_wallet_mandate/__init__.py
customate/rest/open_banking_to_wallet_mandate_payment/__init__.py
customate/rest/open_banking_to_wallet_payment/__init__.py
customate/rest/p2p_currency_exchange/__init__.py
customate/rest/payee/__init__.py
customate/rest/payment/__init__.py
customate/rest/profile/__init__.py
customate/rest/schedule/__init__.py
customate/rest/service_payment/__init__.py
customate/rest/status/__init__.py
customate/rest/transaction/__init__.py
customate/rest/verification/__init__.py
customate/rest/wallet/__init__.py
customate/rest/wallet_to_bank_account_payment/__init__.py
customate/rest/wallet_to_wallet_payment/__init__.py
customate/rest/webhook/__init__.py
customate_sdk-0.0.10.dist-info/LICENSE
customate_sdk-0.0.10.dist-info/METADATA
customate_sdk-0.0.10.dist-info/WHEEL
customate_sdk-0.0.10.dist-info/top_level.txt
customate_sdk-0.0.10.dist-info/RECORD
