Metadata-Version: 2.1
Name: customate-sdk
Version: 0.0.10
Summary: Python software developer kit for Customates API
Home-page: https://github.com/customate/python-sdk
Author: Bobby Stearman
Author-email: bstearman@customate.net
Project-URL: Bug Tracker, https://github.com/customate/python-sdk/issues
Classifier: Programming Language :: Python :: 3
Classifier: License :: OSI Approved :: BSD License
Classifier: Operating System :: OS Independent
Requires-Python: >=3.6
License-File: LICENSE
Requires-Dist: requests (>=2.28.0)
Requires-Dist: six (>=1.16.0)
